simulatortofmu
