Metadata-Version: 1.1
Name: SimulatorToFMU
Version: 1.0.0rc14
Summary: Package for exporting a Simulator as a Functional Mock-up Unit
Home-page: https://github.com/LBNL-ETA/SimulatorToFMU/
Author: Thierry S. Nouidui
Author-email: TSNouidui@lbl.gov
License: 3-clause BSD
Platform: UNKNOWN
Classifier: Development Status :: 5 - Production/Stable
Classifier: Environment :: Console
Classifier: License :: OSI Approved :: BSD License
Classifier: Programming Language :: Python :: 2.7
Classifier: Programming Language :: Python :: 3.5
Classifier: Programming Language :: Python :: 3.6
Classifier: Intended Audience :: End Users/Desktop
Classifier: Intended Audience :: Science/Research
Classifier: Topic :: Scientific/Engineering
Classifier: Topic :: Utilities
